wifi_qr/__init__.py
wifi_qr/scripts/__init__.py
wifi_qr/scripts/wifi_qr.py
wifi_qr_gen-0.1.0.dist-info/LICENSE
wifi_qr_gen-0.1.0.dist-info/METADATA
wifi_qr_gen-0.1.0.dist-info/WHEEL
wifi_qr_gen-0.1.0.dist-info/entry_points.txt
wifi_qr_gen-0.1.0.dist-info/top_level.txt
wifi_qr_gen-0.1.0.dist-info/RECORD
