Metadata-Version: 2.1
Name: wifi-qr-gen
Version: 0.1.0
Summary: UNKNOWN
Home-page: https://github.com/tombuente/wifi-qr
Author: Tom Buente
License: UNKNOWN
Platform: UNKNOWN
License-File: LICENSE
Requires-Dist: Click
Requires-Dist: qrcode
